README.md
setup.py
apache2_vh.egg-info/PKG-INFO
apache2_vh.egg-info/SOURCES.txt
apache2_vh.egg-info/dependency_links.txt
apache2_vh.egg-info/requires.txt
apache2_vh.egg-info/top_level.txt
bin/vh
vh/__init__.py