Metadata-Version: 2.1
Name: apache2-vh
Version: 0.0.1
Summary: Make your virtual host for apache2 automatically in ubuntu
Home-page: https://github.com/MNGemignani/apache2_virtual_host_creator
Author: Mateus Gemignani
Author-email: gemignaniholland@gmail.com
License: UNKNOWN
Keywords: virtual-host apache2 magento2
Platform: UNKNOWN
